{
  "project_info": {
    "project_number": "1098018405967",
    "project_id": "satapp-2101a",
    "storage_bucket": "satapp-2101a.appspot.com"
  },
  "client": [
    {
      "client_info": {
        "mobilesdk_app_id": "1:1098018405967:android:ef66836c7e70ab3318743a",
        "android_client_info": {
          "package_name": "com.sat"
        }
      },
      "oauth_client": [
        {
          "client_id": "1098018405967-ihghhl80pr6hsd57vvet492dku9vbo4h.apps.googleusercontent.com",
          "client_type": 3
        }
      ],
      "api_key": [
        {
          "current_key": "AIzaSyCSIGEkN4PJM_cNln9muvX_1VihKhAf7XI"
        }
      ],
      "services": {
        "appinvite_service": {
          "other_platform_oauth_client": [
            {
              "client_id": "1098018405967-ihghhl80pr6hsd57vvet492dku9vbo4h.apps.googleusercontent.com",
              "client_type": 3
            }
          ]
        }
      }
    }
  ],
  "configuration_version": "1"
}